dashbot/__init__.py
dashbot/alexa.py
dashbot/alexa_vl.py
dashbot/generic.py
dashbot/google.py
dashbot/rasa.py
dashbot/version.py
dashbot-0.0.19.dist-info/LICENSE
dashbot-0.0.19.dist-info/METADATA
dashbot-0.0.19.dist-info/WHEEL
dashbot-0.0.19.dist-info/top_level.txt
dashbot-0.0.19.dist-info/RECORD
