Metadata-Version: 2.1
Name: dashbot
Version: 0.0.19
Summary: Dashbot Python SDK
Home-page: https://github.com/actionably/dashbotpy
Author: Ryan Mortensen
Author-email: ryanm@dashbot.io
License: MIT
Keywords: dashbot,alexasdk,skill
Platform: UNKNOWN
Classifier: Intended Audience :: Developers
Classifier: Topic :: Software Development :: Build Tools
Classifier: License :: OSI Approved :: MIT License
Classifier: Programming Language :: Python :: 2.7
Classifier: Programming Language :: Python :: 3
Requires-Dist: requests
